LICENSE
README.md
setup.py
src/taproot/__init__.py
src/taproot/__main__.py
src/taproot/encryption.py
src/taproot/exceptions.py
src/taproot/hinting.py
src/taproot/payload.py
src/taproot/py.typed
src/taproot/version.py
src/taproot.egg-info/PKG-INFO
src/taproot.egg-info/SOURCES.txt
src/taproot.egg-info/dependency_links.txt
src/taproot.egg-info/entry_points.txt
src/taproot.egg-info/requires.txt
src/taproot.egg-info/top_level.txt
src/taproot/client/__init__.py
src/taproot/client/base.py
src/taproot/client/config.py
src/taproot/client/tap.py
src/taproot/config/__init__.py
src/taproot/config/mixin.py
src/taproot/config/structure.py
src/taproot/constants/__init__.py
src/taproot/constants/binaries.py
src/taproot/constants/defaults.py
src/taproot/constants/diffusion.py
src/taproot/constants/enumerations.py
src/taproot/constants/libraries.py
src/taproot/constants/licenses.py
src/taproot/constants/misc.py
src/taproot/constants/vendors.py
src/taproot/constants/versions.py
src/taproot/modeling/__init__.py
src/taproot/modeling/architectures/__init__.py
src/taproot/modeling/architectures/dit.py
src/taproot/modeling/architectures/mmdit.py
src/taproot/modeling/blocks/__init__.py
src/taproot/modeling/blocks/conv.py
src/taproot/modeling/blocks/dit.py
src/taproot/modeling/embeddings/__init__.py
src/taproot/modeling/embeddings/audio.py
src/taproot/modeling/embeddings/position.py
src/taproot/modeling/embeddings/rotary.py
src/taproot/modeling/embeddings/text.py
src/taproot/modeling/embeddings/timestep.py
src/taproot/modeling/models/__init__.py
src/taproot/modeling/models/cfm.py
src/taproot/modeling/modules/__init__.py
src/taproot/modeling/modules/attention.py
src/taproot/modeling/modules/base.py
src/taproot/modeling/modules/feed_forward.py
src/taproot/modeling/modules/normalization.py
src/taproot/modeling/modules/audio/__init__.py
src/taproot/modeling/modules/audio/mel_spectrogram.py
src/taproot/pretrained/__init__.py
src/taproot/pretrained/text_encoder/__init__.py
src/taproot/pretrained/text_encoder/clip.py
src/taproot/pretrained/text_encoder/llama.py
src/taproot/pretrained/text_encoder/open_clip.py
src/taproot/pretrained/text_encoder/t5.py
src/taproot/pretrained/tokenizer/__init__.py
