Metadata-Version: 2.2
Name: taproot
Version: 0.3.8
Summary: Taproot is a seamlessly scalable AI/ML inference engine designed for deployment across hardware clusters with disparate capabilities.
Author: Benjamin Paine
Author-email: painebenjamin@gmail.com
Classifier: Development Status :: 4 - Beta
Classifier: Intended Audience :: Developers
Classifier: Intended Audience :: Education
Classifier: Intended Audience :: Science/Research
Classifier: License :: OSI Approved :: Apache Software License
Classifier: Operating System :: OS Independent
Classifier: Topic :: Scientific/Engineering :: Artificial Intelligence
Classifier: Programming Language :: Python :: 3
Classifier: Programming Language :: Python :: 3.8
Classifier: Programming Language :: Python :: 3.9
Classifier: Programming Language :: Python :: 3.10
Classifier: Programming Language :: Python :: 3.11
Classifier: Programming Language :: Python :: 3.12
Requires-Python: >=3.8.0
License-File: LICENSE
Requires-Dist: aioconsole
Requires-Dist: async-lru
Requires-Dist: click
Requires-Dist: dbgpu[fuzz]
Requires-Dist: docstring_parser
Requires-Dist: msgpack
Requires-Dist: omegaconf
Requires-Dist: packaging
Requires-Dist: pillow
Requires-Dist: psutil
Requires-Dist: pycryptodome
Requires-Dist: requests
Provides-Extra: av
Requires-Dist: pyav; extra == "av"
Requires-Dist: moviepy<2.0; extra == "av"
Provides-Extra: uv
Requires-Dist: uvloop>=0.18; extra == "uv"
Provides-Extra: jp
Requires-Dist: kanjize; extra == "jp"
Requires-Dist: sudachipy; extra == "jp"
Requires-Dist: sudachidict_full; extra == "jp"
Provides-Extra: ws
Requires-Dist: websockets; extra == "ws"
Provides-Extra: cli
Requires-Dist: tabulate; extra == "cli"
Requires-Dist: termcolor; extra == "cli"
Requires-Dist: tqdm; extra == "cli"
Provides-Extra: http
Requires-Dist: uvicorn; extra == "http"
Requires-Dist: aiohttp; extra == "http"
Requires-Dist: aiodns; extra == "http"
Requires-Dist: starlette; extra == "http"
Provides-Extra: tools
Requires-Dist: pytz; extra == "tools"
Requires-Dist: duckduckgo_search; extra == "tools"
Requires-Dist: beautifulsoup4; extra == "tools"
Dynamic: author
Dynamic: author-email
Dynamic: classifier
Dynamic: description
Dynamic: description-content-type
Dynamic: provides-extra
Dynamic: requires-dist
Dynamic: requires-python
Dynamic: summary
